markov_model_attribution/__init__.py
markov_model_attribution-0.42.dist-info/LICENSE.txt
markov_model_attribution-0.42.dist-info/METADATA
markov_model_attribution-0.42.dist-info/WHEEL
markov_model_attribution-0.42.dist-info/top_level.txt
markov_model_attribution-0.42.dist-info/RECORD
