Metadata-Version: 2.1
Name: markov-model-attribution
Version: 0.42
Summary: A way to build markov-based attribution models in Python.
Home-page: https://github.com/jerednel/markov-chain-attribution
Author: Jeremy Nelson
Author-email: jeremy@mailbox.org
License: MIT
Platform: UNKNOWN
